graphiant_sdk/__init__.py
graphiant_sdk/api_client.py
graphiant_sdk/configuration.py
graphiant_sdk/rest.py
graphiant_sdk/api/__init__.py
graphiant_sdk/api/default_api.py
graphiant_sdk/models/__init__.py
graphiant_sdk/models/account_email_body.py
graphiant_sdk/models/account_info_body.py
graphiant_sdk/models/account_mfa_body.py
graphiant_sdk/models/account_password_body.py
graphiant_sdk/models/ack_createupdate_body.py
graphiant_sdk/models/activity_logs_body.py
graphiant_sdk/models/alarmmute_alarm_id_body.py
graphiant_sdk/models/apps_appsummary_body.py
graphiant_sdk/models/apps_bandwidth_body.py
graphiant_sdk/models/apps_visualization_body.py
graphiant_sdk/models/assistant_addtoconversation_body.py
graphiant_sdk/models/assistant_getconversationdetails_body.py
graphiant_sdk/models/assistant_getconversations_body.py
graphiant_sdk/models/assistant_updateconversationname_body.py
graphiant_sdk/models/assurance_applicationdetailsbyname_body.py
graphiant_sdk/models/assurance_bucketapps_body.py
graphiant_sdk/models/assurance_bucketappservers_body.py
graphiant_sdk/models/assurance_bucketdetails_body.py
graphiant_sdk/models/assurance_buckettopologies_body.py
graphiant_sdk/models/assurance_createclassifiedapplication_body.py
graphiant_sdk/models/assurance_createuserreport_body.py
graphiant_sdk/models/assurance_endpointintel_body.py
graphiant_sdk/models/assurance_flowsummary_body.py
graphiant_sdk/models/assurance_topologyclientsessiondetails_body.py
graphiant_sdk/models/assurance_topologyclientsessions_body.py
graphiant_sdk/models/assurance_topologyclientsummaries_body.py
graphiant_sdk/models/assurance_topologyflows_body.py
graphiant_sdk/models/assurance_topologyinventory_body.py
graphiant_sdk/models/assurance_topologyoverview_body.py
graphiant_sdk/models/assurance_topologyregionsummary_body.py
graphiant_sdk/models/assurance_topologysitesummaries_body.py
graphiant_sdk/models/assurance_updateclassifiedapplication_body.py
graphiant_sdk/models/assurances_global_body.py
graphiant_sdk-25.6.1.dist-info/licenses/LICENSE
graphiant_sdk-25.6.1.dist-info/METADATA
graphiant_sdk-25.6.1.dist-info/WHEEL
graphiant_sdk-25.6.1.dist-info/top_level.txt
graphiant_sdk-25.6.1.dist-info/RECORD
