Metadata-Version: 2.4
Name: graphiant_sdk
Version: 25.6.1
Summary: Python SDK for Graphiant NaaS
Home-page: https://www.graphiant.com
Author: Graphiant Inc
Author-email: support@graphiant.com
License: MIT
Project-URL: Source Code, https://github.com/Graphiant-Inc/graphiant-sdk-python
Keywords: SDK,Graphiant,NaaS
Classifier: Programming Language :: Python :: 3
Classifier: License :: OSI Approved :: MIT License
Classifier: Operating System :: OS Independent
License-File: LICENSE
Requires-Dist: urllib3>=1.15
Requires-Dist: six>=1.10
Requires-Dist: certifi
Requires-Dist: python-dateutil
Dynamic: author
Dynamic: author-email
Dynamic: classifier
Dynamic: description
Dynamic: description-content-type
Dynamic: home-page
Dynamic: keywords
Dynamic: license
Dynamic: license-file
Dynamic: project-url
Dynamic: requires-dist
Dynamic: summary
